cyclotomic/__init__.py
cyclotomic/py.typed
cyclotomic-0.0.post1.dist-info/LICENSE
cyclotomic-0.0.post1.dist-info/METADATA
cyclotomic-0.0.post1.dist-info/WHEEL
cyclotomic-0.0.post1.dist-info/top_level.txt
cyclotomic-0.0.post1.dist-info/RECORD
